{
  "project_info": {
    "project_number": "842640708296",
    "project_id": "togedy-e4645",
    "storage_bucket": "togedy-e4645.firebasestorage.app"
  },
  "client": [
    {
      "client_info": {
        "mobilesdk_app_id": "1:842640708296:android:acbde575012114d11e0bfd",
        "android_client_info": {
          "package_name": "com.together.study"
        }
      },
      "oauth_client": [],
      "api_key": [
        {
          "current_key": "AIzaSyAXskBWB0XpHXWCBOMJfIWAW76iNSZqz9s"
        }
      ],
      "services": {
        "appinvite_service": {
          "other_platform_oauth_client": []
        }
      }
    }
  ],
  "configuration_version": "1"
}